jupyter_docprovider/__init__.py
jupyter_docprovider/_version.py
jupyter_docprovider-2.1.2.data/data/share/jupyter/labextensions/@jupyter/docprovider-extension/package.json
jupyter_docprovider-2.1.2.data/data/share/jupyter/labextensions/@jupyter/docprovider-extension/static/240.1810b1e246bd604b51b2.js
jupyter_docprovider-2.1.2.data/data/share/jupyter/labextensions/@jupyter/docprovider-extension/static/422.3ab44960b241aac9f303.js
jupyter_docprovider-2.1.2.data/data/share/jupyter/labextensions/@jupyter/docprovider-extension/static/444.13de0fd44849e3f7d780.js
jupyter_docprovider-2.1.2.data/data/share/jupyter/labextensions/@jupyter/docprovider-extension/static/703.a9b23bb2dcc109b62003.js
jupyter_docprovider-2.1.2.data/data/share/jupyter/labextensions/@jupyter/docprovider-extension/static/944.eaec77f5cee3f07c3b7f.js
jupyter_docprovider-2.1.2.data/data/share/jupyter/labextensions/@jupyter/docprovider-extension/static/994.bc087314bdabeecb0923.js
jupyter_docprovider-2.1.2.data/data/share/jupyter/labextensions/@jupyter/docprovider-extension/static/remoteEntry.00d6cee65f8f8434f757.js
jupyter_docprovider-2.1.2.data/data/share/jupyter/labextensions/@jupyter/docprovider-extension/static/style.js
jupyter_docprovider-2.1.2.data/data/share/jupyter/labextensions/@jupyter/docprovider-extension/static/third-party-licenses.json
jupyter_docprovider-2.1.2.data/data/share/jupyter/labextensions/@jupyter/docprovider-extension/install.json
jupyter_docprovider-2.1.2.dist-info/METADATA
jupyter_docprovider-2.1.2.dist-info/WHEEL
jupyter_docprovider-2.1.2.dist-info/licenses/LICENSE
jupyter_docprovider-2.1.2.dist-info/RECORD
