Metadata-Version: 2.4
Name: jupyter-docprovider
Version: 2.1.2
Summary: JupyterLab/Jupyter Notebook 7+ extension integrating collaborative shared models.
Project-URL: Documentation, https://jupyterlab-realtime-collaboration.readthedocs.io/
Project-URL: Repository, https://github.com/jupyterlab/jupyter-collaboration
Project-URL: Changelog, https://jupyterlab-realtime-collaboration.readthedocs.io/en/latest/changelog.html
Project-URL: Source, https://github.com/jupyterlab/jupyter-collaboration/tree/main/packages/docprovider-extension
Project-URL: Issues, https://github.com/jupyterlab/jupyter-collaboration/issues/new/choose
Author-email: Jupyter Development Team <jupyter@googlegroups.com>
License: # Licensing terms
License-File: LICENSE
Classifier: Framework :: Jupyter
Classifier: Framework :: Jupyter :: JupyterLab
Classifier: Framework :: Jupyter :: JupyterLab :: 4
Classifier: Framework :: Jupyter :: JupyterLab :: Extensions
Classifier: Framework :: Jupyter :: JupyterLab :: Extensions :: Prebuilt
Classifier: Intended Audience :: Developers
Classifier: Intended Audience :: Science/Research
Classifier: Intended Audience :: System Administrators
Classifier: License :: OSI Approved :: BSD License
Classifier: Programming Language :: Python
Classifier: Programming Language :: Python :: 3.8
Classifier: Programming Language :: Python :: 3.9
Classifier: Programming Language :: Python :: 3.10
Classifier: Programming Language :: Python :: 3.11
Classifier: Programming Language :: Python :: 3.12
Requires-Python: >=3.8
